lstar/__init__.py
lstar/classification_tree.py
lstar/common.py
lstar/learn.py
lstar/test_common.py
lstar/test_learn.py
lstar-1.0.2.dist-info/LICENSE
lstar-1.0.2.dist-info/METADATA
lstar-1.0.2.dist-info/WHEEL
lstar-1.0.2.dist-info/RECORD
