Metadata-Version: 2.1
Name: lstar
Version: 1.0.2
Summary: Python implementation of lstar automata learning algorithm.
License: MIT
Author: Marcell J. Vazquez-Chanlatte
Author-email: mvc@linux.com
Requires-Python: >=3.9,<4.0
Classifier: License :: OSI Approved :: MIT License
Classifier: Programming Language :: Python :: 3
Classifier: Programming Language :: Python :: 3.9
Classifier: Programming Language :: Python :: 3.10
Classifier: Programming Language :: Python :: 3.11
Requires-Dist: attrs (>=22,<23)
Requires-Dist: dfa (>=4,<5)
Requires-Dist: funcy (>=1.12,<2.0)
Requires-Dist: lazytree (>=0.3.2,<0.4.0)
